aioasuswrt/__init__.py
aioasuswrt/asuswrt.py
aioasuswrt/connection.py
aioasuswrt/constant.py
aioasuswrt/helpers.py
aioasuswrt/parsers.py
aioasuswrt/py.typed
aioasuswrt/structure.py
aioasuswrt-2.1.0.dist-info/licenses/LICENSE.md
aioasuswrt-2.1.0.dist-info/METADATA
aioasuswrt-2.1.0.dist-info/WHEEL
aioasuswrt-2.1.0.dist-info/top_level.txt
aioasuswrt-2.1.0.dist-info/RECORD
