Metadata-Version: 2.4
Name: aioasuswrt
Version: 2.1.0
Summary: Api wrapper for Asuswrt https://www.asus.com/ASUSWRT/
Author-email: Magnus Knutas <magnusknutas@gmail.com>
Maintainer-email: Magnus Knutas <magnusknutas@gmail.com>
License-Expression: MIT
Project-URL: Bug Tracker, https://github.com/kennedyshead/aioasuswrt/issues
Project-URL: Changelog, https://github.com/kennedyshead/aioasuswrt/blob/master/CHANGELOG.md
Project-URL: Documentation, https://github.com/kennedyshead/aioasuswrt/blob/master/README.md
Project-URL: Homepage, https://github.com/kennedyshead/aioasuswrt
Project-URL: Repository, https://github.com/kennedyshead/aioasuswrt.git
Keywords: Asus,development,hass,homeassistant,iot,router
Classifier: Development Status :: 3 - Alpha
Classifier: Intended Audience :: Developers
Classifier: Programming Language :: Python :: 3
Classifier: Topic :: Software Development :: Libraries
Requires-Python: >=3.13
License-File: LICENSE.md
Requires-Dist: asyncssh
Requires-Dist: bcrypt
Dynamic: license-file
